odoo/addons/stock_removal_location_by_priority/README.rst
odoo/addons/stock_removal_location_by_priority/__init__.py
odoo/addons/stock_removal_location_by_priority/__manifest__.py
odoo/addons/stock_removal_location_by_priority/init_hook.py
odoo/addons/stock_removal_location_by_priority/i18n/de.po
odoo/addons/stock_removal_location_by_priority/i18n/es.po
odoo/addons/stock_removal_location_by_priority/i18n/fi.po
odoo/addons/stock_removal_location_by_priority/i18n/fr.po
odoo/addons/stock_removal_location_by_priority/i18n/it.po
odoo/addons/stock_removal_location_by_priority/i18n/pt_BR.po
odoo/addons/stock_removal_location_by_priority/i18n/ro.po
odoo/addons/stock_removal_location_by_priority/i18n/sl.po
odoo/addons/stock_removal_location_by_priority/i18n/stock_removal_location_by_priority.pot
odoo/addons/stock_removal_location_by_priority/i18n/zh_CN.po
odoo/addons/stock_removal_location_by_priority/models/__init__.py
odoo/addons/stock_removal_location_by_priority/models/res_config_settings.py
odoo/addons/stock_removal_location_by_priority/models/stock_location.py
odoo/addons/stock_removal_location_by_priority/models/stock_quant.py
odoo/addons/stock_removal_location_by_priority/readme/CONFIGURE.rst
odoo/addons/stock_removal_location_by_priority/readme/CONTRIBUTORS.rst
odoo/addons/stock_removal_location_by_priority/readme/DESCRIPTION.rst
odoo/addons/stock_removal_location_by_priority/readme/USAGE.rst
odoo/addons/stock_removal_location_by_priority/security/stock_security.xml
odoo/addons/stock_removal_location_by_priority/static/description/icon.png
odoo/addons/stock_removal_location_by_priority/static/description/index.html
odoo/addons/stock_removal_location_by_priority/tests/__init__.py
odoo/addons/stock_removal_location_by_priority/tests/test_stock_removal_location_by_priority.py
odoo/addons/stock_removal_location_by_priority/views/res_config_settings_views.xml
odoo/addons/stock_removal_location_by_priority/views/stock_location_view.xml
odoo14_addon_stock_removal_location_by_priority-14.0.1.0.1.dev7.dist-info/METADATA
odoo14_addon_stock_removal_location_by_priority-14.0.1.0.1.dev7.dist-info/WHEEL
odoo14_addon_stock_removal_location_by_priority-14.0.1.0.1.dev7.dist-info/top_level.txt
odoo14_addon_stock_removal_location_by_priority-14.0.1.0.1.dev7.dist-info/RECORD
